list_user_permissions_for_aws_idc/__init__.py
list_user_permissions_for_aws_idc/file_output_utils.py
list_user_permissions_for_aws_idc/list_user_permissions.py
list_user_permissions_for_aws_idc/list_user_permissions_for_aws_idc.py
list_user_permissions_for_aws_idc/list_utils.py
list_user_permissions_for_aws_idc-0.1.3.dist-info/LICENSE
list_user_permissions_for_aws_idc-0.1.3.dist-info/METADATA
list_user_permissions_for_aws_idc-0.1.3.dist-info/WHEEL
list_user_permissions_for_aws_idc-0.1.3.dist-info/entry_points.txt
list_user_permissions_for_aws_idc-0.1.3.dist-info/RECORD
