Metadata-Version: 2.1
Name: list-user-permissions-for-aws-idc
Version: 0.1.3
Summary: List users and permissions inside AWS Identity Center
Home-page: https://github.com/aws-samples/list-user-permissions-for-aws-idc
License: MIT
Keywords: aws,idc,sso
Author: Keith Rozario
Author-email: krozario@amazon.com
Requires-Python: >=3.8,<4.0
Classifier: License :: OSI Approved :: MIT License
Classifier: Programming Language :: Python :: 3
Classifier: Programming Language :: Python :: 3.8
Classifier: Programming Language :: Python :: 3.9
Classifier: Programming Language :: Python :: 3.10
Classifier: Programming Language :: Python :: 3.11
Classifier: Programming Language :: Python :: 3.12
Requires-Dist: boto3 (>=1.34.91,<2.0.0)
Requires-Dist: click (>=8.1.7,<9.0.0)
Project-URL: Repository, https://github.com/aws-samples/list-user-permissions-for-aws-idc
